uniparser_beserman_lat/__init__.py
uniparser_beserman_lat/data_default/__init__.py
uniparser_beserman_lat/data_default/bad_analyses.txt
uniparser_beserman_lat/data_default/beserman.cg3
uniparser_beserman_lat/data_default/lexemes.txt
uniparser_beserman_lat/data_default/paradigms.txt
uniparser_beserman_lat-2.1.12.dist-info/LICENSE
uniparser_beserman_lat-2.1.12.dist-info/METADATA
uniparser_beserman_lat-2.1.12.dist-info/WHEEL
uniparser_beserman_lat-2.1.12.dist-info/top_level.txt
uniparser_beserman_lat-2.1.12.dist-info/RECORD
