Metadata-Version: 2.2
Name: uniparser-beserman-lat
Version: 2.1.12
Summary: Rule-based morphological analysis for Beserman (Latin-based script)
Home-page: https://github.com/timarkh/uniparser-grammar-beserman
Author: Timofey Arkhangelskiy
Author-email: timarkh@gmail.com
Project-URL: Bug Tracker, https://github.com/timarkh/uniparser-grammar-beserman/issues
Classifier: Programming Language :: Python :: 3
Classifier: License :: OSI Approved :: MIT License
Classifier: Operating System :: OS Independent
Classifier: Intended Audience :: Science/Research
Classifier: Topic :: Text Processing :: Linguistic
Requires-Python: >=3.7
License-File: LICENSE
Requires-Dist: uniparser-morph>=2.6.4
Requires-Dist: importlib-resources
